aspeak-6.1.0.data/scripts/aspeak
aspeak-6.1.0.dist-info/METADATA
aspeak-6.1.0.dist-info/RECORD
aspeak-6.1.0.dist-info/WHEEL
aspeak-6.1.0.dist-info/WHEEL
aspeak/__init__.py
aspeak/__init__.pyi
aspeak/aspeak.abi3.so
aspeak/py.typed
