Metadata-Version: 2.4
Name: aspeak
Version: 6.1.0
Summary: A simple text-to-speech client for Azure TTS API.
Keywords: speech-synthesis,aspeak,tts,text-to-speech,audio
Home-Page: https://github.com/kxxt/aspeak
Author: kxxt <rsworktech@outlook.com>
Author-email: kxxt <rsworktech@outlook.com>
License: MIT
Project-URL: Source Code, https://github.com/kxxt/aspeak
